zik_dl/__init__.py
zik_dl/arguments.py
zik_dl/downloader.py
zik_dl/files_manager.py
zik_dl/settings.py
zik_dl/utils.py
zik_dl-0.6.0.dist-info/LICENSE
zik_dl-0.6.0.dist-info/METADATA
zik_dl-0.6.0.dist-info/WHEEL
zik_dl-0.6.0.dist-info/entry_points.txt
zik_dl-0.6.0.dist-info/top_level.txt
zik_dl-0.6.0.dist-info/RECORD
