Metadata-Version: 2.1
Name: zik-dl
Version: 0.6.0
Summary: Command-line program to download music from YouTube and other websites.
Home-page: https://gitlab.com/rafutek/zik-dl
Author: Raphaël Roy
Author-email: raphaelroy@tutanota.com
License: GNU AGPLv3
Keywords: music,download,cli,youtube-dl
Platform: UNKNOWN
Classifier: Programming Language :: Python :: 3
Classifier: License :: OSI Approved :: GNU Affero General Public License v3
Classifier: Topic :: Multimedia :: Sound/Audio
Classifier: Topic :: Internet
Classifier: Intended Audience :: End Users/Desktop
License-File: LICENSE
Requires-Dist: yt-dlp
Requires-Dist: music-tag
Requires-Dist: pillow
Provides-Extra: dev
Requires-Dist: black ; extra == 'dev'
Requires-Dist: pytest ; extra == 'dev'
Requires-Dist: pytest-cov ; extra == 'dev'
Requires-Dist: twine ; extra == 'dev'
